odoo/addons/pos_auto_invoice/README.rst
odoo/addons/pos_auto_invoice/__init__.py
odoo/addons/pos_auto_invoice/__manifest__.py
odoo/addons/pos_auto_invoice/i18n/it.po
odoo/addons/pos_auto_invoice/i18n/pos_auto_invoice.pot
odoo/addons/pos_auto_invoice/models/__init__.py
odoo/addons/pos_auto_invoice/models/pos_config.py
odoo/addons/pos_auto_invoice/models/res_config_settings.py
odoo/addons/pos_auto_invoice/readme/CONFIGURE.rst
odoo/addons/pos_auto_invoice/readme/CONTRIBUTORS.rst
odoo/addons/pos_auto_invoice/readme/DESCRIPTION.rst
odoo/addons/pos_auto_invoice/static/description/icon.png
odoo/addons/pos_auto_invoice/static/description/index.html
odoo/addons/pos_auto_invoice/static/src/js/models.esm.js
odoo/addons/pos_auto_invoice/views/res_config_settings_view.xml
odoo_addon_pos_auto_invoice-16.0.1.0.0.9.dist-info/METADATA
odoo_addon_pos_auto_invoice-16.0.1.0.0.9.dist-info/WHEEL
odoo_addon_pos_auto_invoice-16.0.1.0.0.9.dist-info/top_level.txt
odoo_addon_pos_auto_invoice-16.0.1.0.0.9.dist-info/RECORD
