Metadata-Version: 2.1
Name: odoo-addon-pos_auto_invoice
Version: 16.0.1.0.0.9
Summary: Allow to set POS orders as to-invoice by default
Home-page: https://github.com/OCA/pos
Author: Coop IT Easy SC, Odoo Community Association (OCA)
Author-email: support@odoo-community.org
License: AGPL-3
Classifier: Programming Language :: Python
Classifier: Framework :: Odoo
Classifier: Framework :: Odoo :: 16.0
Classifier: License :: OSI Approved :: GNU Affero General Public License v3
Requires-Python: >=3.10
Requires-Dist: odoo<16.1dev,>=16.0a
